proxr_protocol/__init__.py
proxr_protocol/__version__.py
proxr_protocol/_bank_control.py
proxr_protocol/_parsing.py
proxr_protocol/_relay_control.py
proxr_protocol/_unpacker.py
proxr_protocol/py.typed
proxr_protocol/tools.py
proxr_protocol-2023.8.0.dist-info/METADATA
proxr_protocol-2023.8.0.dist-info/WHEEL
proxr_protocol-2023.8.0.dist-info/licenses/LICENSE
proxr_protocol-2023.8.0.dist-info/RECORD
