Metadata-Version: 2.1
Name: proxr-protocol
Version: 2023.8.0
Project-URL: Source, https://github.com/yaq-project/proxr-protocol
Project-URL: Issues, https://github.com/yaq-project/proxr-protocol/issues
License-Expression: MIT
License-File: LICENSE
Classifier: Development Status :: 2 - Pre-Alpha
Classifier: Intended Audience :: Science/Research
Classifier: License :: OSI Approved :: MIT License
Classifier: Natural Language :: English
Classifier: Programming Language :: Python :: 3
Classifier: Programming Language :: Python :: 3.7
Classifier: Programming Language :: Python :: 3.8
Classifier: Programming Language :: Python :: 3.9
Classifier: Programming Language :: Python :: 3.10
Classifier: Programming Language :: Python :: 3.11
Classifier: Topic :: Scientific/Engineering
Requires-Python: >=3.7
Provides-Extra: dev
Requires-Dist: black; extra == 'dev'
Requires-Dist: pre-commit; extra == 'dev'
